tissue_detection/__init__.py
tissue_detection/template.py
tissue_detection/tpe.py
tissue_detection/examples/A13_firstframe.tif
tissue_detection/examples/__init__.py
tissue_detection/templates/__init__.py
tissue_detection/templates/tpe1_template.tif
tissue_detection-0.0.2.dist-info/LICENSE
tissue_detection-0.0.2.dist-info/METADATA
tissue_detection-0.0.2.dist-info/WHEEL
tissue_detection-0.0.2.dist-info/top_level.txt
tissue_detection-0.0.2.dist-info/RECORD
